cifar10_client/__init__.py
cifar10_client/cli.py
cifar10_client/client.py
cifar10_client-0.1.7.dist-info/LICENSE
cifar10_client-0.1.7.dist-info/METADATA
cifar10_client-0.1.7.dist-info/WHEEL
cifar10_client-0.1.7.dist-info/top_level.txt
cifar10_client-0.1.7.dist-info/RECORD
