Metadata-Version: 2.1
Name: cifar10-client
Version: 0.1.7
Summary: Client for CIFAR-10 image classification API
Author: Your Name
Author-email: Your Name <your.email@example.com>
Requires-Python: >=3.7
License-File: LICENSE
Requires-Dist: requests>=2.25.0
Requires-Dist: click>=8.0.0
Requires-Dist: rich>=10.0.0
